openspace/__init__.py
openspace/src/__init__.py
openspace/src/api.py
openspace/src/socketwrapper.py
openspace/src/topic.py
openspace_api-0.1.3.dist-info/licenses/LICENSE.md
openspace_api-0.1.3.dist-info/METADATA
openspace_api-0.1.3.dist-info/WHEEL
openspace_api-0.1.3.dist-info/top_level.txt
openspace_api-0.1.3.dist-info/RECORD
