Metadata-Version: 2.4
Name: openspace-api
Version: 0.1.3
Summary: Python library to interface with OpenSpace using sockets
Author-email: OpenSpace developers <api-python-aaaamu4sytkkayaafonqgmouri@team-openspace.slack.com>
Project-URL: Homepage, https://openspaceproject.com
Project-URL: OpenSpace, https://github.com/OpenSpace/OpenSpace
Project-URL: Source, https://github.com/OpenSpace/openspace-api-python/
Classifier: Programming Language :: Python :: 3
Classifier: License :: OSI Approved :: MIT License
Classifier: Operating System :: OS Independent
Requires-Python: >=3.10
License-File: LICENSE.md
Dynamic: license-file
